grading_tools/__init__.py
grading_tools/checkers.py
grading_tools/feedback/english.py
grading_tools/graders.py
grading_tools/loaders.py
grading_tools/utils.py
grading_tools-0.21.3.dist-info/METADATA
grading_tools-0.21.3.dist-info/WHEEL
grading_tools-0.21.3.dist-info/RECORD
